{
  "cluster_name": "orcs-ecs-qa",
  "task_family": "orcs-api-qa",
  "awslogs_group ": "orcs-ecs-syslogs-qa",
  "app_name": "orcs-api",
  "region": "us-east-1",
  "lb_type": "alb",
  "lb_name_light": "orcs-ecs-qa-l",
  "lb_name_dark": "orcs-ecs-qa-l",
  "lb_target_group_light": "orcs-ecs-qa-l",
  "lb_target_group_dark": "orcs-ecs-qa-l",
  "iam_role": "orcs-ecs-qa-us-east-1_role",
  "task_role":"ecsTaskExecutionRole",
  "service_count": 2,
  "host_port": 0,
  "container_port": 8080,
  "wait_max_attempts": 60,
  "wait_delay_sec": 10,
  "rolling_max_percent": 200,
  "rolling_healthy_percent": 100,
  "health_check_grace_period": 0,
  "service_autoscaling_enabled": true,
  "service_autoscale_max": 10,
  "service_autoscale_min": 2,
  "service_autoscale_alarm": "RequestCountPerTarget",
  "service_autoscale_namespace": "AWS/ApplicationELB",
  "service_autoscale_dimensions": {"LoadBalancer": "app/orcs-ecs-qa-l/d3cba92bfbe86d01","TargetGroup": "targetgroup/orcs-ecs-qa-l/be12d1d7743e11f4 "},
  "service_autoscale_statistic": "Sum",
  "service_autoscale_y_axis_unit": "None",
  "service_autoscale_iam_role": "ecsAutoscaleRole",
  "service_autoscale_low_threshold": 600,
  "service_autoscale_high_threshold": 1000,
  "service_autoscale_cooldown": 60,
  "service_autoscale_increment_count": 1,
  "service_autoscale_decrement_count": 1,
  "service_autoscale_scale_up_eval_periods": 5,
  "service_autoscale_scale_down_eval_periods": 15,
  "service_autoscale_scale_up_period": 60,
  "service_autoscale_scale_down_period": 60
}
